{"type":"FeatureCollection","name":"Storesstores_1","crs":{"type":"name","properties":{"name":"urn:ogc:def:crs:OGC:1.3:CRS84"}},"features":[{"type":"Feature","properties":{"fid":"1","id":"0001A908C8327FE3793C","Name":"معدات سيسكو ترانس","description":null},"geometry":{"type":"Point","coordinates":[31.767954781133554,31.450146943419796]}},{"type":"Feature","properties":{"fid":"2","id":"080424F53D327FE3D991","Name":"معدات ميد سوفت"},"geometry":{"type":"Point","coordinates":[31.76730542427153,31.450552425034065]}},{"type":"Feature","properties":{"fid":"3","id":"0FB3884AFF327FE40DBC","Name":"معدات مارين لوجيستيك"},"geometry":{"type":"Point","coordinates":[31.766437515546489,31.451275430056626]}},{"type":"Feature","properties":{"fid":"4","id":"0D2F5B7308327FE458B5","Name":"معدات سي سيرفيس"},"geometry":{"type":"Point","coordinates":[31.765754646295797,31.451951384303765]}},{"type":"Feature","properties":{"fid":"5","id":"082E9D3003327FE47F74","Name":"معدات إيريك"},"geometry":{"type":"Point","coordinates":[31.765193286787699,31.452396868779037]}},{"type":"Feature","properties":{"fid":"6","id":"0E61ECCC07327FE595AE","Name":"ساحة معدات رويال سي"},"geometry":{"type":"Point","coordinates":[31.772779053878583,31.448683882505186]}},{"type":"Feature","properties":{"fid":"7","id":"039A8F85C1327FE5ECCC","Name":"السد العالى"},"geometry":{"type":"Point","coordinates":[31.772537495759689,31.447938970688323]}},{"type":"Feature","properties":{"fid":"8","id":"0E85CD9921327FE64A10","Name":"مارين لوجيستيك"},"geometry":{"type":"Point","coordinates":[31.772887646735491,31.447665064334704]}},{"type":"Feature","properties":{"fid":"9","id":"0F1A0031F7327FE67791","Name":"معدات الشروق"},"geometry":{"type":"Point","coordinates":[31.77292673655645,31.448198489669863]}},{"type":"Feature","properties":{"fid":"10","id":"0C7C359761327FE6C1CD","Name":"السد العالى"},"geometry":{"type":"Point","coordinates":[31.77316931180977,31.448442299991342]}},{"type":"Feature","properties":{"fid":"11","id":"097E177900327FE6DBEF","Name":"الشركة البحرية محمد فتحى"},"geometry":{"type":"Point","coordinates":[31.773430190125818,31.448166297950554]}},{"type":"Feature","properties":{"fid":"12","id":"0FD9536940327FE717B7","Name":"معدات سيسكو"},"geometry":{"type":"Point","coordinates":[31.773557677367616,31.448461382680854]}},{"type":"Feature","properties":{"fid":"13","id":"0515758BDA327FE76A6E","Name":"معدات المجد مجدى بصار"},"geometry":{"type":"Point","coordinates":[31.773201564150625,31.447400479411435]}},{"type":"Feature","properties":{"fid":"14","id":"09DDF79B76327FE7ADFE","Name":"معدات البدري"},"geometry":{"type":"Point","coordinates":[31.774279770364103,31.446534694557993]}},{"type":"Feature","properties":{"fid":"15","id":"01443D74A0327FE800F4","Name":"معدات سي سيرفيس"},"geometry":{"type":"Point","coordinates":[31.775346172142239,31.446249083156207]}},{"type":"Feature","properties":{"fid":"16","id":"0DDF2535DB327FE839ED","Name":"معدات سنابل"},"geometry":{"type":"Point","coordinates":[31.774977264506497,31.446510994775764]}},{"type":"Feature","properties":{"fid":"17","id":"055B8FFA80327FE8AC65","Name":"معدات الطماوى - المصرية"},"geometry":{"type":"Point","coordinates":[31.774519260046109,31.44690971087163]}},{"type":"Feature","properties":{"fid":"18","id":"0C54901B36327FE96124","Name":"معدات سنابل"},"geometry":{"type":"Point","coordinates":[31.774198053921673,31.447265216845896]}},{"type":"Feature","properties":{"fid":"19","id":"0E1784E0B7327FEB8D66","Name":"معدات المجد لتكرير الزيوت"},"geometry":{"type":"Point","coordinates":[31.77556494156908,31.446758367731345]}},{"type":"Feature","properties":{"fid":"20","id":"0210ED00AE327FD9DC0F","Name":"مخزن سيسكو"},"geometry":{"type":"Point","coordinates":[31.776091141552499,31.449557716362705]}},{"type":"Feature","properties":{"fid":"21","id":"0A81A7C995327FDA9815","Name":"مخزن كايرو ثري"},"geometry":{"type":"Point","coordinates":[31.774845949743284,31.448638237305008]}},{"type":"Feature","properties":{"fid":"22","id":"08116097DF327FDB37B0","Name":"مخزن سي ترانس"},"geometry":{"type":"Point","coordinates":[31.775278244932284,31.45068429831235]}},{"type":"Feature","properties":{"fid":"23","id":"00519120BD327FDB723B","Name":"مخزن كايروثري ايه","description":"15000 مساحة مخصصه"},"geometry":{"type":"Point","coordinates":[31.774907623580585,31.450115883158638]}},{"type":"Feature","properties":{"fid":"24","id":"0004CAEBE0327FE1062C","Name":"مخزن المجد لتكرير الزيوت"},"geometry":{"type":"Point","coordinates":[31.776238036419791,31.447471246220449]}},{"type":"Feature","properties":{"fid":"25","id":"0B5042C51F327FE1465A","Name":"مخزن كايرو ثري ايه"},"geometry":{"type":"Point","coordinates":[31.777073489150354,31.448098425298117]}},{"type":"Feature","properties":{"fid":"26","id":"0A942CC7F8327FE170DA","Name":"مخزن سنابل"},"geometry":{"type":"Point","coordinates":[31.777609639325593,31.448689583112021]}},{"type":"Feature","properties":{"fid":"27","id":"083D7913522D64EEAF3B","Name":"مخزن الدقهلية"},"geometry":{"type":"Point","coordinates":[31.769224056172309,31.444809967870256]}},{"type":"Feature","properties":{"fid":"28","id":"031A866A082D64EED3BF","Name":"مخزن كايرو ثري ايه"},"geometry":{"type":"Point","coordinates":[31.769756303563408,31.445288756774659]}},{"type":"Feature","properties":{"fid":"29","id":"045ACE24752D64EF090F","Name":"مخزن سيسكو"},"geometry":{"type":"Point","coordinates":[31.770193781901089,31.445685720176993]}},{"type":"Feature","properties":{"fid":"30","id":"041EFF04C02D64EF652F","Name":"مخزن سي سيرفيس"},"geometry":{"type":"Point","coordinates":[31.770557445260966,31.446108710424209]}},{"type":"Feature","properties":{"fid":"31","id":"0C32F7EF122D64EFC113","Name":"مخزن سي سيرفيس"},"geometry":{"type":"Point","coordinates":[31.771035601153013,31.446393121319087]}},{"type":"Feature","properties":{"fid":"32","id":"042FDAFD0B2D64EFE919","Name":"مخزن ميد سوفت"},"geometry":{"type":"Point","coordinates":[31.771433593965281,31.446767983132162]}},{"type":"Feature","properties":{"fid":"33","id":"0FE74A898B2D64F23D0E","Name":"مخزن مهمل الهيئة"},"geometry":{"type":"Point","coordinates":[31.77397978964429,31.446116708614543]}},{"type":"Feature","properties":{"fid":"34","id":"008895FCF02D64F40959","Name":"مخزن تابع للهيئة"},"geometry":{"type":"Point","coordinates":[31.77312908689867,31.446971486061894]}},{"type":"Feature","properties":{"fid":"35","id":"068D23908C2D64F42F16","Name":"مخزن تابع للهيئة"},"geometry":{"type":"Point","coordinates":[31.773014630865763,31.446767554557717]}},{"type":"Feature","properties":{"fid":"36","id":"065CB2F8D72D64FC98BA","Name":"مخزن ميد سوفت"},"geometry":{"type":"Point","coordinates":[31.770960091108574,31.444878778286334]}},{"type":"Feature","properties":{"fid":"37","id":"0079655FAD2D64FCBD0A","Name":"مخزن كايرو ثري ايه"},"geometry":{"type":"Point","coordinates":[31.771674638525631,31.445491768892609]}},{"type":"Feature","properties":{"fid":"38","id":"0BF06635AF2D64FCE791","Name":"مخزن كايرو ثري ايه"},"geometry":{"type":"Point","coordinates":[31.772398035497311,31.446004289145236]}},{"type":"Feature","properties":{"fid":"39","id":"01FCD250EC2D650175CE","Name":"مخزن سيسكو ترانس"},"geometry":{"type":"Point","coordinates":[31.772879657405412,31.455032266056485]}},{"type":"Feature","properties":{"fid":"40","id":"07B6239FF72D6501A263","Name":"مخزن سيسكو ترانس"},"geometry":{"type":"Point","coordinates":[31.772284956894691,31.455539544245923]}},{"type":"Feature","properties":{"fid":"41","id":"04E68830682D6501D6E3","Name":"مخزن سي سيرفيس"},"geometry":{"type":"Point","coordinates":[31.771451323655512,31.4562215691431]}},{"type":"Feature","properties":{"fid":"42","id":"042CAD464E2D650228C0","Name":"مخزن شركة سنابل"},"geometry":{"type":"Point","coordinates":[31.770660955121034,31.457039352410984]}},{"type":"Feature","properties":{"fid":"43","id":"075446C0852D650260C5","Name":"مخزن شركة سنابل"},"geometry":{"type":"Point","coordinates":[31.769706768599541,31.457813233906634]}},{"type":"Feature","properties":{"fid":"44","id":"0B65A7F1682D65052EFE","Name":"مخزن كايروثري ايه"},"geometry":{"type":"Point","coordinates":[31.767464455569122,31.449270916147192]}},{"type":"Feature","properties":{"fid":"45","id":"0C144BDA0A2D65091A6D","Name":"مخزن إيجيبت ستون"},"geometry":{"type":"Point","coordinates":[31.76850001932965,31.448243381225559]}},{"type":"Feature","properties":{"fid":"46","id":"0F62F35D352D6509652B","Name":"مخزن كايرو ثري ايه"},"geometry":{"type":"Point","coordinates":[31.766643211052688,31.449913762904323]}},{"type":"Feature","properties":{"fid":"47","id":"0C98022A6C2D6509D412","Name":"مخزن الجيزة للدخان"},"geometry":{"type":"Point","coordinates":[31.76488913765672,31.450838906955113]}},{"type":"Feature","properties":{"fid":"48","id":"0B58A01F262D650D6AEC","Name":"مخزن كايرو ثري ايه"},"geometry":{"type":"Point","coordinates":[31.76578781685512,31.450561769959766]}},{"type":"Feature","properties":{"fid":"49","id":"00E002DDA22D650EBFB5","Name":"مخازن كايرو ثري ايه"},"geometry":{"type":"Point","coordinates":[31.764651395934635,31.451566440678224]}},{"type":"Feature","properties":{"fid":"50","id":"0EB98928EB2D650F2625","Name":"مخازن كايرو ثري ايه"},"geometry":{"type":"Point","coordinates":[31.764284084794813,31.45108330532684]}},{"type":"Feature","properties":{"fid":"51","id":"08D171A4592D650FED72","Name":"مخزن لاج"},"geometry":{"type":"Point","coordinates":[31.766152127005466,31.449425673684036]}},{"type":"Feature","properties":{"fid":"52","id":"0229E96EA92D65102848","Name":"مخزن سيسكو ترانس"},"geometry":{"type":"Point","coordinates":[31.7654248048227,31.448839216866261]}},{"type":"Feature","properties":{"fid":"53","id":"010649F2212D65121A41","Name":"مخزن الوطنية"},"geometry":{"type":"Point","coordinates":[31.762489904522859,31.451227500392541]}},{"type":"Feature","properties":{"fid":"54","id":"0CE9B426932D65125D09","Name":"مخزن كايرو ثري ايه"},"geometry":{"type":"Point","coordinates":[31.763542832561409,31.450390318382357]}},{"type":"Feature","properties":{"fid":"55","id":"04C38697AE2D69F0BD7A","Name":"مخزن الصوامع"},"geometry":{"type":"Point","coordinates":[31.766165165541576,31.469568383603118]}},{"type":"Feature","properties":{"fid":"56","id":"09867BEC062D69F0F9C4","Name":"مخزن الصوامع"},"geometry":{"type":"Point","coordinates":[31.764463886201391,31.470196921989103]}},{"type":"Feature","properties":{"fid":"57","id":"0CC76D787A2D69F15971","Name":"مخزن الرحاب"},"geometry":{"type":"Point","coordinates":[31.767361222001991,31.468050535598099]}},{"type":"Feature","properties":{"fid":"58","id":"0FA0A2BA8D2D69F1A900","Name":"مخزن كايرو ثري ايه"},"geometry":{"type":"Point","coordinates":[31.770334667844537,31.467718371131635]}},{"type":"Feature","properties":{"fid":"59","id":"07AD2A69DE2D69F71B7D","Name":"مخازن كايرو ثري ايه"},"geometry":{"type":"Point","coordinates":[31.772504602198843,31.464165480978696]}},{"type":"Feature","properties":{"fid":"60","id":"02A72D12DB327FE24E46","Name":"مخزن سي سيرفيس"},"geometry":{"type":"Point","coordinates":[31.77797474700607,31.449315385888429]}},{"type":"Feature","properties":{"fid":"61","id":"02F76D0C2A327FE27F66","Name":"مخزن سيسكو ترانس"},"geometry":{"type":"Point","coordinates":[31.777295851356939,31.450028657417114]}},{"type":"Feature","properties":{"fid":"62","id":"0E1FA175B62D647A3716","Name":"السويسرية"},"geometry":{"type":"Point","coordinates":[31.775729741728597,31.453403766214265]}},{"type":"Feature","properties":{"fid":"63","id":"017E7CD9C72D647FBEAC","Name":"سنابل للشحن والتفريغ"},"geometry":{"type":"Point","coordinates":[31.774847924716333,31.453283352661838]}},{"type":"Feature","properties":{"fid":"64","id":"0F859EB13D2D64809157","Name":"الفارس العربي"},"geometry":{"type":"Point","coordinates":[31.775052823158539,31.453953328901214]}},{"type":"Feature","properties":{"fid":"65","id":"067BE03AA32D648173D5","Name":"إسبريا مصر"},"geometry":{"type":"Point","coordinates":[31.774678549628849,31.454380431815398]}},{"type":"Feature","properties":{"fid":"66","id":"095B9911B82D6481F0D6","Name":"رويال للبتروكيماويات"},"geometry":{"type":"Point","coordinates":[31.77396672740824,31.454889460996505]}},{"type":"Feature","properties":{"fid":"67","id":"03886011C12D648289FB","Name":"أجواء"},"geometry":{"type":"Point","coordinates":[31.77335577906117,31.455667214455367]}},{"type":"Feature","properties":{"fid":"68","id":"0AC24274492D6483A7F3","Name":"عافية للزيوت"},"geometry":{"type":"Point","coordinates":[31.772473231538889,31.456340179335253]}},{"type":"Feature","properties":{"fid":"69","id":"0471A6122E2D64846AC1","Name":"إفكو"},"geometry":{"type":"Point","coordinates":[31.771826062778892,31.457016669793823]}},{"type":"Feature","properties":{"fid":"70","id":"0AEFCD1A202D6484F448","Name":"الفا مصر"},"geometry":{"type":"Point","coordinates":[31.770876992205494,31.457638050135913]}},{"type":"Feature","properties":{"fid":"71","id":"06D6B470D52D64859E16","Name":"المتحدة للزيوت"},"geometry":{"type":"Point","coordinates":[31.76795879625061,31.460256794686991]}},{"type":"Feature","properties":{"fid":"72","id":"0A422965772D64860101","Name":"أرما"},"geometry":{"type":"Point","coordinates":[31.76910304492251,31.459281605862053]}},{"type":"Feature","properties":{"fid":"73","id":"06474041A72D6486DB6B","Name":"الدلتا للسكر"},"geometry":{"type":"Point","coordinates":[31.76869504507652,31.458696301730818]}},{"type":"Feature","properties":{"fid":"74","id":"0EBEB128FD2D64872C2B","Name":"الدقهلية"},"geometry":{"type":"Point","coordinates":[31.767974079094039,31.459215937178147]}},{"type":"Feature","properties":{"fid":"75","id":"0AAEF779C62D6493ECC8","Name":"مخازن كايرو ثري ايه"},"geometry":{"type":"Point","coordinates":[31.774270206663491,31.45258056709098]}},{"type":"Feature","properties":{"fid":"76","id":"0666FD0EE82D64952AA1","Name":"محمد فتحي"},"geometry":{"type":"Point","coordinates":[31.772983038254868,31.453648752530992]}},{"type":"Feature","properties":{"fid":"77","id":"065B5353592D6496A327","Name":"سنابل"},"geometry":{"type":"Point","coordinates":[31.771633871092959,31.454968817120811]}},{"type":"Feature","properties":{"fid":"78","id":"0247FD35692D6496FDC4","Name":"مخزن كايروثري ايه"},"geometry":{"type":"Point","coordinates":[31.773542912491845,31.454438463923918]}},{"type":"Feature","properties":{"fid":"79","id":"04AD9382B22D6497D55F","Name":"مخزن كايرو ثري ايه"},"geometry":{"type":"Point","coordinates":[31.769374748164608,31.456813401720503]}},{"type":"Feature","properties":{"fid":"80","id":"0498D28D022D649881B9","Name":"مخزن سيسكو"},"geometry":{"type":"Point","coordinates":[31.766950423911869,31.45900131181185]}},{"type":"Feature","properties":{"fid":"81","id":"09157AF4F92D6498DBB9","Name":"مخزن كايرو ثري ايه"},"geometry":{"type":"Point","coordinates":[31.76812965753555,31.458066864498523]}},{"type":"Feature","properties":{"fid":"82","id":"0F56C6917E2D64B33418","Name":"ورشة معدات البدري"},"geometry":{"type":"Point","coordinates":[31.770284811803219,31.448544621609155]}},{"type":"Feature","properties":{"fid":"83","id":"0994C7339B2D64B3A66E","Name":"ورشة معدات النجاح"},"geometry":{"type":"Point","coordinates":[31.770610889759958,31.448706017066261]}},{"type":"Feature","properties":{"fid":"84","id":"01080E92CD2D64B40A21","Name":"ورشة معدات الطماوى"},"geometry":{"type":"Point","coordinates":[31.77085824644529,31.448945184029952]}},{"type":"Feature","properties":{"fid":"85","id":"06C392C4BA2D64B4467F","Name":"ورشة معدات سيسكو"},"geometry":{"type":"Point","coordinates":[31.77115667239023,31.44921991739124]}},{"type":"Feature","properties":{"fid":"86","id":"09030230E62D64B7CCD2","Name":"مارين لوجيستيك"},"geometry":{"type":"Point","coordinates":[31.782701871292861,31.453835025845226]}},{"type":"Feature","properties":{"fid":"87","id":"04B2ECB8182D64CDFB75","Name":"سنابل"},"geometry":{"type":"Point","coordinates":[31.780362535021428,31.450549946850757]}},{"type":"Feature","properties":{"fid":"88","id":"0275DB73F12D64CE3181","Name":"الصوفي"},"geometry":{"type":"Point","coordinates":[31.780897884905027,31.451013868176002]}},{"type":"Feature","properties":{"fid":"89","id":"064466BDE42D64CE5B14","Name":"الشروق"},"geometry":{"type":"Point","coordinates":[31.781803865638121,31.451751741579503]}},{"type":"Feature","properties":{"fid":"90","id":"000BD62C6F2D64CEEFF8","Name":"ميد سوفت"},"geometry":{"type":"Point","coordinates":[31.782747753139624,31.452505173305433]}},{"type":"Feature","properties":{"fid":"91","id":"04C9DC12B72D64CF3750","Name":"سيسكو ترانس"},"geometry":{"type":"Point","coordinates":[31.780800690346108,31.452178272307496]}},{"type":"Feature","properties":{"fid":"92","id":"0D38DD95AB2D7903A002","Name":"الفارس العربي"},"geometry":{"type":"Point","coordinates":[31.769995523901546,31.458370612250778]}},{"type":"Feature","properties":{"fid":"93","id":"075445FC8C2D6A1E4788","Name":"شركة الرحاب"},"geometry":{"type":"Point","coordinates":[31.768129788449386,31.474888680936132]}},{"type":"Feature","properties":{"fid":"94","id":"04105B30842D64F0CC10","Name":"مخزن الأهلية"},"geometry":{"type":"Point","coordinates":[31.772734951544155,31.446239353586815]}},{"type":"Feature","properties":{"fid":"95","id":"08FC0FF4EF303F4A79E5","Name":"هانى فور تريد W25/5"},"geometry":{"type":"Point","coordinates":[31.775454295775095,31.449033165139795]}},{"type":"Feature","properties":{"fid":"96","id":"013AE835472D64877C45","Name":"المنصورة للراتنجات"},"geometry":{"type":"Point","coordinates":[31.767341755393598,31.45983048895431]}},{"type":"Feature","properties":{"fid":"97","id":"06225426872D650DB5D9","Name":"شركة هجر بوتا"},"geometry":{"type":"Point","coordinates":[31.767257586211681,31.44864009832532]}}]}
